pjsua2/__init__.py
pjsua2/_pjsua2.pyd
pjsua2/msvcp140.dll
pjsua2/msvcp140_1.dll
pjsua2/msvcp140_2.dll
pjsua2/pjsua2.py
pjsua2/vcruntime140.dll
pjsua2/vcruntime140_1.dll
pjsua2_wheel-2.15.3.dist-info/METADATA
pjsua2_wheel-2.15.3.dist-info/WHEEL
pjsua2_wheel-2.15.3.dist-info/top_level.txt
pjsua2_wheel-2.15.3.dist-info/RECORD
