Metadata-Version: 2.4
Name: pjsua2-wheel
Version: 2.15.3
Summary: Pre-built Windows wheels for PJSUA2 with bundled VC++ Runtime - Python bindings for PJSIP (SIP/VoIP Library)
Home-page: https://www.pjsip.org
Author: Ramanan
Author-email: ramanan182004@gmail.com
License: GPL-2.0-or-later
Project-URL: Homepage, https://www.pjsip.org
Project-URL: Repository, https://github.com/pjsip/pjproject
Project-URL: Documentation, https://docs.pjsip.org
Classifier: Development Status :: 5 - Production/Stable
Classifier: Intended Audience :: Developers
Classifier: Topic :: Communications :: Telephony
Classifier: Topic :: Software Development :: Libraries :: Python Modules
Classifier: License :: OSI Approved :: GNU General Public License v2 or later (GPLv2+)
Classifier: Programming Language :: Python :: 3
Classifier: Programming Language :: Python :: 3.9
Classifier: Programming Language :: Python :: 3.10
Classifier: Programming Language :: Python :: 3.11
Classifier: Programming Language :: Python :: 3.12
Classifier: Programming Language :: C++
Classifier: Operating System :: Microsoft :: Windows
Requires-Python: >=3.9
Dynamic: author
Dynamic: author-email
Dynamic: classifier
Dynamic: description
Dynamic: description-content-type
Dynamic: home-page
Dynamic: license
Dynamic: project-url
Dynamic: requires-python
Dynamic: summary
